<resources xmlns:xsi="http://www.w3.org/2001/XMLSchema-instance">
	<string key="99B_Yonas" gender="M" rel_version="Quest_MSQ2_Brightwood">Yonas Alazar</string>
	<string key="99B_Yonas_title" rel_version="Quest_MSQ2_Brightwood">Protecteur des âmes</string>
	<string key="99B_Galahad" gender="M" rel_version="Quest_MSQ2_Brightwood">Sire Galahad</string>
	<string key="99B_Galahad_title" rel_version="Quest_MSQ2_Brightwood">Chevalier errant</string>
	<string key="99B_Pennyfather" gender="M" rel_version="Quest_MSQ2_Brightwood">Tunstall Pennyfather</string>
	<string key="99B_Pennyfather_title" rel_version="Quest_MSQ2_Brightwood">Maire de Calvary</string>
	<string key="99B_Grace" gender="F" rel_version="Quest_MSQ2_Brightwood">Grace O'Malley</string>
	<string key="99B_Grace_title" rel_version="Quest_MSQ2_Brightwood">Pirate</string>
	<string key="99B_Sun" gender="F" rel_version="Quest_MSQ2_Brightwood">Sun Fuchun</string>
	<string key="99B_Sun_title" rel_version="Quest_MSQ2_Brightwood">Érudite de Nerécaille</string>
	<string key="UmbertoHuman_SubName" gender="M" rel_version="Quest_MSQ2_Brightwood">Frère Umberto</string>
	<string key="UmbertoSpirit_SubName" gender="M" rel_version="Quest_MSQ2_Brightwood">Esprit d'Umberto</string>
	<string key="99B_MorgenGrave_A">La tombe d'une beauté</string>
	<string key="99B_MorgenGrave_B">La tombe d'un père de famille</string>
	<string key="99B_MorgenGrave_C">La tombe d'un chasseur</string>
	<string key="99B_gravestone_interactoverride">Déposer souvenir</string>
</resources>

